nonebot_plugin_bfvplayerlist/__init__.py
nonebot_plugin_bfvplayerlist/background-image.jpg
nonebot_plugin_bfvplayerlist/html.html
nonebot_plugin_bfvplayerlist-0.2.1.dist-info/LICENSE
nonebot_plugin_bfvplayerlist-0.2.1.dist-info/METADATA
nonebot_plugin_bfvplayerlist-0.2.1.dist-info/WHEEL
nonebot_plugin_bfvplayerlist-0.2.1.dist-info/RECORD
