Metadata-Version: 2.3
Name: nonebot-plugin-bfvplayerlist
Version: 0.2.1
Summary: A onebot plugin for querying bfv server players
License: MIT
Author: llbuxudong 3513392931@qq.com
Requires-Python: >=3.8,<4.0
Classifier: License :: OSI Approved :: MIT License
Classifier: Programming Language :: Python :: 3
Classifier: Programming Language :: Python :: 3.8
Classifier: Programming Language :: Python :: 3.9
Classifier: Programming Language :: Python :: 3.10
Classifier: Programming Language :: Python :: 3.11
Classifier: Programming Language :: Python :: 3.12
Classifier: Programming Language :: Python :: 3.13
Requires-Dist: httpx (>=0.23.0,<=1.0.0)
Requires-Dist: nonebot-adapter-onebot (>=2.2.0,<3.0.0)
Requires-Dist: nonebot-plugin-htmlrender (>=0.6.0)
Requires-Dist: nonebot2 (>=2.3.0)
